{
  "_note1": "KEEP THIS FILE! Check it into a version control system (VCS) like git.",
  "_note2": "ObjectBox manages crucial IDs for your object model. See docs for details.",
  "_note3": "If you have VCS merge conflicts, you must resolve them according to ObjectBox docs.",
  "entities": [
    {
      "id": "2:632816148333431856",
      "lastPropertyId": "3:8816725207231477272",
      "name": "ProjectMessage",
      "properties": [
        {
          "id": "1:4412632841902862663",
          "name": "id",
          "type": 6,
          "flags": 1
        },
        {
          "id": "2:5841859942318752357",
          "name": "projectId",
          "type": 9
        },
        {
          "id": "3:8816725207231477272",
          "name": "name",
          "type": 9
        }
      ],
      "relations": []
    },
    {
      "id": "3:2613446829570482106",
      "lastPropertyId": "3:6581292721200000415",
      "name": "UserResponse",
      "properties": [
        {
          "id": "1:5591223865823536897",
          "name": "id",
          "type": 6,
          "flags": 1
        },
        {
          "id": "2:4267189600675961536",
          "name": "userId",
          "type": 9
        },
        {
          "id": "3:6581292721200000415",
          "name": "nickname",
          "type": 9
        }
      ],
      "relations": []
    },
    {
      "id": "5:9176327664423535516",
      "lastPropertyId": "7:2559704926572998253",
      "name": "MessageModel",
      "properties": [
        {
          "id": "1:8441717303719906635",
          "name": "id",
          "type": 6,
          "flags": 1
        },
        {
          "id": "2:4216460832316152973",
          "name": "currentUserId",
          "type": 9
        },
        {
          "id": "3:3707706288675256417",
          "name": "messageId",
          "type": 9
        },
        {
          "id": "4:7921868239712666450",
          "name": "senderId",
          "type": 11,
          "flags": 520,
          "indexId": "5:2233796622705494105",
          "relationTarget": "UserResponse"
        },
        {
          "id": "5:5249949683172450250",
          "name": "projectId",
          "type": 11,
          "flags": 520,
          "indexId": "6:5333179155948424398",
          "relationTarget": "ProjectMessage"
        },
        {
          "id": "6:4733467294600499986",
          "name": "content",
          "type": 9
        },
        {
          "id": "7:2559704926572998253",
          "name": "sentIn",
          "type": 10
        }
      ],
      "relations": []
    }
  ],
  "lastEntityId": "5:9176327664423535516",
  "lastIndexId": "6:5333179155948424398",
  "lastRelationId": "0:0",
  "lastSequenceId": "0:0",
  "modelVersion": 5,
  "modelVersionParserMinimum": 5,
  "retiredEntityUids": [
    3694419320491295600,
    4607073361781796973
  ],
  "retiredIndexUids": [],
  "retiredPropertyUids": [
    6543103656144520450,
    4753695960815210549,
    3037320259593609535,
    6847899715388605132,
    7228614411897435110,
    7417395419298307988,
    7347372675632564917,
    4819443787248771219,
    7750818519451931965,
    3991461923309328802,
    3303759470612521738,
    6223497650481154069,
    691881582770152483,
    6182178949642222496,
    249132271780913112
  ],
  "retiredRelationUids": [],
  "version": 1
}